docassemble.MassAccess-0.4.1-py3.10-nspkg.pth
docassemble/MassAccess/__init__.py
docassemble/MassAccess/data/questions/efile-account-interview.yml
docassemble/MassAccess/data/questions/feedback.yml
docassemble/MassAccess/data/questions/massaccess.yml
docassemble/MassAccess/data/sources/README.md
docassemble/MassAccess/data/static/README.md
docassemble/MassAccess/data/static/colors.css
docassemble/MassAccess/data/static/custom_504.html
docassemble/MassAccess/data/static/lit_logo_light.png
docassemble/MassAccess/data/static/mass_icon.png
docassemble/MassAccess/data/static/seal.jpg
docassemble/MassAccess/data/static/dev_favicon/android-chrome-192x192.png
docassemble/MassAccess/data/static/dev_favicon/android-chrome-512x512.png
docassemble/MassAccess/data/static/dev_favicon/apple-touch-icon.png
docassemble/MassAccess/data/static/dev_favicon/browserconfig.xml
docassemble/MassAccess/data/static/dev_favicon/favicon-16x16.png
docassemble/MassAccess/data/static/dev_favicon/favicon-32x32.png
docassemble/MassAccess/data/static/dev_favicon/favicon.ico
docassemble/MassAccess/data/static/dev_favicon/flame-dev.svg
docassemble/MassAccess/data/static/dev_favicon/mstile-144x144.png
docassemble/MassAccess/data/static/dev_favicon/mstile-150x150.png
docassemble/MassAccess/data/static/dev_favicon/mstile-310x150.png
docassemble/MassAccess/data/static/dev_favicon/mstile-310x310.png
docassemble/MassAccess/data/static/dev_favicon/mstile-70x70.png
docassemble/MassAccess/data/static/dev_favicon/safari-pinned-tab.svg
docassemble/MassAccess/data/static/dev_favicon/site.webmanifest
docassemble/MassAccess/data/static/favicon/android-chrome-192x192.png
docassemble/MassAccess/data/static/favicon/android-chrome-512x512.png
docassemble/MassAccess/data/static/favicon/apple-touch-icon.png
docassemble/MassAccess/data/static/favicon/browserconfig.xml
docassemble/MassAccess/data/static/favicon/favicon-16x16.png
docassemble/MassAccess/data/static/favicon/favicon-32x32.png
docassemble.MassAccess-0.4.1.dist-info/LICENSE
docassemble.MassAccess-0.4.1.dist-info/METADATA
docassemble.MassAccess-0.4.1.dist-info/WHEEL
docassemble.MassAccess-0.4.1.dist-info/namespace_packages.txt
docassemble.MassAccess-0.4.1.dist-info/top_level.txt
docassemble.MassAccess-0.4.1.dist-info/RECORD
