Metadata-Version: 2.1
Name: docassemble.MassAccess
Version: 0.4.1
Summary: A docassemble project using the AssemblyLine package in combination with the ALMassachusetts package.
Home-page: https://suffolklitlab.org/docassemble-AssemblyLine-documentation/docs
Author: MassAccess
Author-email: litlab@suffolk.edu
License: The MIT License (MIT)
License-File: LICENSE
Requires-Dist: docassemble.ALMassachusetts >=0.1.2
Requires-Dist: docassemble.GithubFeedbackForm >=0.2.0
